cfsiv_utils/__init__.py
cfsiv_utils/filehandling.py
cfsiv_utils/log_handling.py
cfsiv_utils/time_strings.py
cfsiv_utils/WebScraping.py
cfsiv_utils-0.1.3.dist-info/LICENSE
cfsiv_utils-0.1.3.dist-info/WHEEL
cfsiv_utils-0.1.3.dist-info/METADATA
cfsiv_utils-0.1.3.dist-info/RECORD
