Metadata-Version: 2.1
Name: cfsiv-utils
Version: 0.1.3
Summary: A collection of Logging, Time, Date, Filehandling and webscraping functions
License: MIT
Author: Conrad Storz
Author-email: conradstorz@gmail.com
Requires-Python: >=3.9,<4.0
Classifier: License :: OSI Approved :: MIT License
Classifier: Programming Language :: Python :: 3
Classifier: Programming Language :: Python :: 3.10
Classifier: Programming Language :: Python :: 3.9
Requires-Dist: DateTime (>=4.3,<5.0)
Requires-Dist: black (>=21.12b0,<22.0)
Requires-Dist: bs4 (>=0.0.1,<0.0.2)
Requires-Dist: dateparser (>=1.1.0,<2.0.0)
Requires-Dist: loguru (>=0.5.3,<0.6.0)
Requires-Dist: pathlib (>=1.0.1,<2.0.0)
Requires-Dist: python-dateutil (>=2.8.2,<3.0.0)
Requires-Dist: pytz (>=2021.3,<2022.0)
Requires-Dist: requests (>=2.27.0,<3.0.0)
Requires-Dist: requests-toolbelt (>=0.9.1,<0.10.0)
Requires-Dist: tqdm (>=4.62.3,<5.0.0)
